Lab6/bcd_to_xs3.vhd
library IEEE;
use IEEE.STD_LOGIC_1164.ALL;
use IEEE.NUMERIC_STD.ALL;

entity BCD_TO_XS3 is
    Port (
        BCD : in  STD_LOGIC_VECTOR(3 downto 0);
        XS3 : out STD_LOGIC_VECTOR(3 downto 0)
    );
end BCD_TO_XS3;

architecture Behavioral of BCD_TO_XS3 is
begin

    process(BCD)
    begin
        if unsigned(BCD) <= 9 then
            XS3 <= std_logic_vector(unsigned(BCD) + 3);
        else
            XS3 <= "0000";  -- Invalid BCD
        end if;
    end process;

end Behavioral;

Lab6/bcd_xs3_tb.vhd
library IEEE;
use IEEE.STD_LOGIC_1164.ALL;

entity BCD_XS3_TB is
end entity BCD_XS3_TB;

architecture Simulation of BCD_XS3_TB is

    signal BCD : STD_LOGIC_VECTOR(3 downto 0) := "0000";
    signal XS3 : STD_LOGIC_VECTOR(3 downto 0);

begin

    DUT : entity work.BCD_TO_XS3
        port map (
            BCD => BCD,
            XS3 => XS3
        );

    STIMULUS : process
    begin
        BCD <= "0000"; wait for 10 ns;
        BCD <= "0001"; wait for 10 ns;
        BCD <= "0010"; wait for 10 ns;
        BCD <= "0011"; wait for 10 ns;
        BCD <= "0100"; wait for 10 ns;
        BCD <= "0101"; wait for 10 ns;
        BCD <= "0110"; wait for 10 ns;
        BCD <= "0111"; wait for 10 ns;
        BCD <= "1000"; wait for 10 ns;
        BCD <= "1001"; wait for 10 ns;
        BCD <= "1010"; wait for 10 ns;

        wait;
    end process;

end architecture Simulation;

Lab6/bcd_xs3.vcd
$date
  Wed Jul 08 10:40:01 2026
$end
$version
  GHDL v0
$end
$timescale
  1 fs
$end
$scope module standard $end
$upscope $end
$scope module std_logic_1164 $end
$upscope $end
$scope module numeric_std $end
$upscope $end
$scope module bcd_xs3_tb $end
$var reg 4 ! bcd[3:0] $end
$var reg 4 " xs3[3:0] $end
$scope module dut $end
$var reg 4 # bcd[3:0] $end
$var reg 4 $ xs3[3:0] $end
$upscope $end
$upscope $end
$enddefinitions $end
#0
b0000 !
b0011 "
b0000 #
b0011 $
#10000000
b0001 !
b0100 "
b0001 #
b0100 $
#20000000
b0010 !
b0101 "
b0010 #
b0101 $
#30000000
b0011 !
b0110 "
b0011 #
b0110 $
#40000000
b0100 !
b0111 "
b0100 #
b0111 $
#50000000
b0101 !
b1000 "
b0101 #
b1000 $
#60000000
b0110 !
b1001 "
b0110 #
b1001 $
#70000000
b0111 !
b1010 "
b0111 #
b1010 $
#80000000
b1000 !
b1011 "
b1000 #
b1011 $
#90000000
b1001 !
b1100 "
b1001 #
b1100 $
#100000000
b1010 !
b0000 "
b1010 #
b0000 $
